local_exception_logger/__init__.py
local_exception_logger/core.py
local_exception_logger-0.1.2.dist-info/METADATA
local_exception_logger-0.1.2.dist-info/WHEEL
local_exception_logger-0.1.2.dist-info/top_level.txt
local_exception_logger-0.1.2.dist-info/RECORD
